[
    {
        "letter": "Ğ",
        "landmarks": [
            {
                "x": 0.0,
                "y": 0.0,
                "z": 0.0
            },
            {
                "x": 0.0653676688671112,
                "y": -0.026763439178466797,
                "z": -0.00727657174968499
            },
            {
                "x": 0.1067003607749939,
                "y": -0.09192800521850586,
                "z": -0.00900026496776718
            },
            {
                "x": 0.13496798276901245,
                "y": -0.14546972513198853,
                "z": -0.013663718405155123
            },
            {
                "x": 0.16187986731529236,
                "y": -0.1862688660621643,
                "z": -0.018289244662014426
            },
            {
                "x": 0.03233301639556885,
                "y": -0.23417460918426514,
                "z": 0.015229448747845709
            },
            {
                "x": 0.046299248933792114,
                "y": -0.3205581307411194,
                "z": 0.002147060890706598
            },
            {
                "x": 0.06866437196731567,
                "y": -0.37081195414066315,
                "z": -0.012736212390450419
            },
            {
                "x": 0.09044161438941956,
                "y": -0.4118584990501404,
                "z": -0.02270691741534847
            },
            {
                "x": 0.0067854225635528564,
                "y": -0.24955955147743225,
                "z": 0.005421935186745941
            },
            {
                "x": 0.02355903387069702,
                "y": -0.3541968762874603,
                "z": -0.003602645753858269
            },
            {
                "x": 0.049223095178604126,
                "y": -0.4196029156446457,
                "z": -0.015693365524498404
            },
            {
                "x": 0.0736224353313446,
                "y": -0.47135666012763977,
                "z": -0.024574705327836455
            },
            {
                "x": -0.020925402641296387,
                "y": -0.25043654441833496,
                "z": -0.00889591120460409
            },
            {
                "x": -0.014774978160858154,
                "y": -0.35746850073337555,
                "z": -0.020809953029242934
            },
            {
                "x": 0.005446881055831909,
                "y": -0.4262455850839615,
                "z": -0.0317972031635918
            },
            {
                "x": 0.026972413063049316,
                "y": -0.479733943939209,
                "z": -0.038526008765188635
            },
            {
                "x": -0.051371946930885315,
                "y": -0.23756331205368042,
                "z": -0.024968582133737982
            },
            {
                "x": -0.05465570092201233,
                "y": -0.32745805382728577,
                "z": -0.034631798903433264
            },
            {
                "x": -0.04455074667930603,
                "y": -0.3897978812456131,
                "z": -0.03859236736127514
            },
            {
                "x": -0.028178691864013672,
                "y": -0.44270578026771545,
                "z": -0.04125372965165752
            }
        ]
    }
]