[
    {
        "letter": "Ğ",
        "landmarks": [
            {
                "x": 0.0,
                "y": 0.0,
                "z": 0.0
            },
            {
                "x": 0.09589967131614685,
                "y": 0.006581723690032959,
                "z": -0.05047471741067966
            },
            {
                "x": 0.18117928504943848,
                "y": -0.004686176776885986,
                "z": -0.09001649090873798
            },
            {
                "x": 0.2554181218147278,
                "y": 0.00901806354522705,
                "z": -0.12762100169288715
            },
            {
                "x": 0.32133644819259644,
                "y": 0.04063820838928223,
                "z": -0.1687139786206444
            },
            {
                "x": 0.1829151213169098,
                "y": -0.20939704775810242,
                "z": -0.0832449115239342
            },
            {
                "x": 0.25254446268081665,
                "y": -0.32140612602233887,
                "z": -0.12877052197086414
            },
            {
                "x": 0.291070818901062,
                "y": -0.3961464762687683,
                "z": -0.1602904267035683
            },
            {
                "x": 0.32334691286087036,
                "y": -0.46673932671546936,
                "z": -0.18408457109558185
            },
            {
                "x": 0.12470453977584839,
                "y": -0.2516936659812927,
                "z": -0.09332898178922733
            },
            {
                "x": 0.16685962677001953,
                "y": -0.40184155106544495,
                "z": -0.13449857303726276
            },
            {
                "x": 0.1966080665588379,
                "y": -0.5034979581832886,
                "z": -0.16571883031951984
            },
            {
                "x": 0.22009426355361938,
                "y": -0.5937462449073792,
                "z": -0.18949603209125598
            },
            {
                "x": 0.055710673332214355,
                "y": -0.25104963779449463,
                "z": -0.10713700869905551
            },
            {
                "x": 0.07219195365905762,
                "y": -0.4018360376358032,
                "z": -0.1506739921294411
            },
            {
                "x": 0.08678427338600159,
                "y": -0.5084861814975739,
                "z": -0.1861797786675652
            },
            {
                "x": 0.10309234261512756,
                "y": -0.6048245429992676,
                "z": -0.21149618098365863
            },
            {
                "x": -0.01513536274433136,
                "y": -0.21557822823524475,
                "z": -0.12425065705406269
            },
            {
                "x": -0.0487598180770874,
                "y": -0.3187890648841858,
                "z": -0.16987497279274066
            },
            {
                "x": -0.07260005176067352,
                "y": -0.3926509916782379,
                "z": -0.19475842187034687
            },
            {
                "x": -0.08841812610626221,
                "y": -0.46462397277355194,
                "z": -0.2110353476725777
            }
        ]
    }
]